resourcer/__init__.py
resourcer-0.1.5.dist-info/LICENSE
resourcer-0.1.5.dist-info/METADATA
resourcer-0.1.5.dist-info/WHEEL
resourcer-0.1.5.dist-info/top_level.txt
resourcer-0.1.5.dist-info/RECORD
