Metadata-Version: 2.1
Name: resourcer
Version: 0.1.5
Summary: A simple wrapper around 'requests'
Home-page: https://github.com/fiazsami/resourcer
Author: Fiaz Sami
License: UNKNOWN
Platform: UNKNOWN
Classifier: Programming Language :: Python :: 3
Classifier: License :: OSI Approved :: MIT License
Classifier: Operating System :: OS Independent
Requires-Python: >=3.6
Requires-Dist: requests
